LICENSE
MANIFEST.in
README.md
setup.cfg
setup.py
tap_nice_incontact/__init__.py
tap_nice_incontact/client.py
tap_nice_incontact/discover.py
tap_nice_incontact/streams.py
tap_nice_incontact/sync.py
tap_nice_incontact/transform.py
tap_nice_incontact.egg-info/PKG-INFO
tap_nice_incontact.egg-info/SOURCES.txt
tap_nice_incontact.egg-info/dependency_links.txt
tap_nice_incontact.egg-info/entry_points.txt
tap_nice_incontact.egg-info/requires.txt
tap_nice_incontact.egg-info/top_level.txt
tap_nice_incontact/schemas/contacts_completed.json
tap_nice_incontact/schemas/skills_sla_summary.json
tap_nice_incontact/schemas/skills_summary.json
tap_nice_incontact/schemas/teams_performance_total.json
tap_nice_incontact/schemas/wfm_agents.json
tap_nice_incontact/schemas/wfm_agents_schedule_adherence.json
tap_nice_incontact/schemas/wfm_agents_scorecards.json
tap_nice_incontact/schemas/wfm_skills_agent_performance.json
tap_nice_incontact/schemas/wfm_skills_contacts.json
tap_nice_incontact/schemas/wfm_skills_dialer_contacts.json
tests/test_convert_data_types.py
tests/test_transform_iso8601_durations.py